{"numero":"917693108","data-deposito":"10/07/2019","data-concessao":"03/03/2020","data-vigencia":"03/03/2030","despachos":{"despacho":{"codigo":"IPAS158","nome":"Concessão de registro"}},"titulares":{"titular":{"nome-razao-social":"ELEXSANDRA COSTA SILVA","pais":"BR","uf":"MG"}},"marca":{"apresentacao":"Mista","natureza":"De Serviço","nome":"ROUTE BIKER'S BRASIL"},"classes-vienna":{"edicao":"4","classe-vienna":[{"codigo":"2.9.23"},{"codigo":"27.5.25"}]},"lista-classe-nice":{"classe-nice":{"codigo":"41","especificacao":"Organização de espetáculos [shows] [serviços de empresário]; Produção de shows; Serviços de acampamentos desportivos; Serviços de clubes [lazer ou educação]; Serviços de divertimento; Serviços de entretenimento; Serviços de lazer e entretenimento, prestados a título de assistência social; Serviços de representação de classe, a saber, promoção de lazer e entretenimento;","status":"Deferido"}},"procurador":"Elexsandra costa silva"}