{"numero":"917858867","data-deposito":"31/07/2019","data-concessao":"03/03/2020","data-vigencia":"03/03/2030","despachos":{"despacho":{"codigo":"IPAS158","nome":"Concessão de registro"}},"titulares":{"titular":{"nome-razao-social":"PLANETA ALEGRIA COMUNICAÇÕES E PRODUÇÕES DE AUDIO E VIDEO LTDA.ME","pais":"BR","uf":"SP"}},"marca":{"apresentacao":"Mista","natureza":"De Serviço","nome":"TELECO & TECO"},"classes-vienna":{"edicao":"4","classe-vienna":{"codigo":"2.1.7"}},"lista-classe-nice":{"classe-nice":{"codigo":"41","especificacao":"Apresentação de espetáculos ao vivo; Apresentação de espetáculos circenses; Apresentação de espetáculos de variedades; Composição de canções; Filmagem em vídeo; Informações sobre entretenimento [lazer]; Informações sobre recreação; Organização de espetáculos [shows] [serviços de empresário]; Organização de exposições para fins culturais ou educativos; Planejamento de festas [serviços de entretenimento]; Produção de filmes, exceto para fins de publicidade; Produção de programas de rádio e televisão; Produção de programas de televisão e rádio; Produção de shows; Produção musical; Produções teatrais; Programas de entretenimento de rádio; Programas de entretenimento de televisão; Provimento de serviços para jogos eletrônicos; Provimento de serviços para jogos on-line [computadores]; Provimento de publicações eletrônicas on-line [não downloadable]; Publicação de livros; Publicação on-line de livros e periódicos eletrônicos; Serviços de composição musical; Serviços de divertimento; Serviços de discoteca; Serviços de entretenimento; Serviços de dj; Serviços de espetáculos; Serviços de estúdios de gravação; Serviços de parques de diversão; Fornecimento de filmes, não baixáveis, através de serviços de vídeo sob demanda; Fornecimento de programas de televisão, não baixáveis, através de serviços de vídeo sob demanda; Organização de eventos de assunção de personagens [cosplay] para fins de entretenimento; Apresentação de canto; Cantor(a); Distribuição de filmes; Serviços de edição de vídeos para eventos; Direção de filmes, exceto filmes publicitários; serviços de companhia teatral; serviços de conjunto musical [serviços de entretenimento]; Provimento de vídeos online, não baixáveis; Agente artístico; literário e cultural [promotor de evento]; Animação de festa; Assessoria, consultoria e informação em entretenimento [lazer]; Banda de música [serviços de entretenimento]; Clube de livro e disco [lazer ou educação]; Clube de vídeo game e vídeo cassete [lazer ou educação]; Desfile de moda somente para entretenimento; Disc-jóquei; Empresário [organização e produção de espetáculos]; Gravações musicais em VHS/DVD/CD [serviços de estúdio]; Grupo musical; Guias eletrônicos, revistas, jornais e boletins oferecidos ao consumidor online [somente para acesso, sem possibilidade de download]; Parque de diversão; Promotor de eventos [se artísticos/culturais]; Provimento de web site disponibilizando fotos, áudio e vídeo não downloadble [serviço de entretenimento]; Serviços de concepção de programas de TV/rádio; Serviços de lazer e entretenimento, prestados a título de assistência social;","status":"Deferido"}},"procurador":"ALBERTO TOMASOLI DA SILVA BRAGA"}