{"numero":"918024013","despachos":{"despacho":{"codigo":"IPAS024","nome":"Indeferimento do pedido","texto-complementar":"A marca reproduz ou imita os seguintes registros de terceiros, sendo, portanto, irregistrável de acordo com o inciso XIX do Art. 124 da LPI: Processo 901010367 (SUIPREMIUM) e Processo 901010391 (SUIPREMIUM). Art. 124 - Não são registráveis como marca: XIX - reprodução ou imitação, no todo ou em parte, ainda que com acréscimo, de marca alheia registrada, para distinguir ou certificar produto ou serviço idêntico, semelhante ou afim, suscetível de causar confusão ou associação com marca alheia;"}},"titulares":{"titular":{"nome-razao-social":"SÃO SALVADOR ALIMENTOS S/A","pais":"BR","uf":"GO"}},"lista-classe-nice":{"classe-nice":{"codigo":"31","especificacao":"Algarobilho para consumo animal; Alimento para animais confinados; Alimento para gado; Alimentos para animais; Alimentos para animais de estimação; Alimentos para pássaros; Animais de criação; Animais vivos; Aves de criação vivas; Bebidas para animais de estimação; Biscoitos para cães; Cal para forragem animal; Ervas para consumo humano ou animal; Farinha de amendoim para animais; Farinha de linhaça para consumo animal; Farinha de peixe para consumo animal; Farinha para animais; Forragens fortificantes para animais; Gérmen de trigo para consumo animal; Grãos para consumo animal; Leveduras para consumo animal; Linhaça para consumo animal; Massa de farelos para consumo animal; Milho; Objetos comestíveis para mascar para animais; Ovos de siba [sépia] para aves; Papas para engorda de animais de criação; Preparações para engorda de animais; Preparações para engorda de animais de criação; Preparações para postura de aves de criação; Produtos para camas para gado; Resíduos de destilaria para consumo animal; Sêmola para aves de criação; Subprodutos do processamento de cereais, para consumo animal; Torta de amendoim para animais; Torta de colza para gado; Torta de milho para gado; Torta para gado; Algas, não processadas, para consumo humano ou animal; Lixa para animais de estimação [areia higiênica]; Areia higiênica aromática para animais de estimação; Alfafa [forragem para animais]; Alpiste; Biscoito para animal de estimação; Bloco de sal para animais; Carne para animal [alimento para animais]; Cereal para animal; Farinha de osso para animal; Granulado sanitário para animal; Ração para animal; Torta [alimento para animal]; Vegetal para animal;","status":"Deferido"}},"procurador":"Vilage Marcas e Patentes  Ltda"}