{"numero":"919094996","data-deposito":"27/01/2020","despachos":{"despacho":{"codigo":"IPAS009","nome":"Publicação de pedido de registro para oposição (exame formal concluído)"}},"titulares":{"titular":{"nome-razao-social":"INSTITUTO COGNORAMA","pais":"BR","uf":"ES"}},"marca":{"apresentacao":"Mista","natureza":"Produtos e/ou Serviço","nome":"COGNORAMA"},"classes-vienna":{"edicao":"4","classe-vienna":{"codigo":"26.1.5"}},"lista-classe-nice":{"classe-nice":{"codigo":"41","especificacao":"Cursos livres [ensino];Serviços de educação;Serviços de ensino;","status":"Pendente"}},"procurador":"Precisa Marcas e Patentes LTDA - ME"}