{"numero":"919070965","data-deposito":"23/01/2020","despachos":{"despacho":{"codigo":"IPAS009","nome":"Publicação de pedido de registro para oposição (exame formal concluído)"}},"titulares":{"titular":{"nome-razao-social":"KLAUS SIEBJE","pais":"BR","uf":"PR"}},"marca":{"apresentacao":"Nominativa","natureza":"Produtos e/ou Serviço","nome":"ENERGIAS DA TERRA"},"lista-classe-nice":{"classe-nice":{"codigo":"03","especificacao":"Adstringentes para uso cosmético;Água de cheiro;Água de colônia [eau de Cologne];Água de lavanda;Água de toalete [eaux de toilette];Água dentifrícia;Água depilatória;Água oxigenada [peróxido de hidrogênio] para uso cosmético;Álcool antisséptico em gel para higiene pessoal;Algodão para a higiene pessoal;Algodão para uso cosmético;Antimofo [desumidificador à base de cloreto de cálcio para uso doméstico];Antimofo com fragrância [desumidificador à base de cloreto de cálcio para uso doméstico];Antitranspirantes [produtos de toalete];Argila para estética;Aromáticos [óleos essenciais];Aromatizadores de ambiente com varetas [difusores de aromas];Bases para perfumes de flores;Batons para os lábios;Composto fluorado para higiene bucal;Condicionador [cosmético];Condicionadores para cabelos;Cosmético à base de algas;Cosméticos;Cosméticos para as sobrancelhas;Cosméticos para crianças;Creme desengraxante para limpeza de mãos;Creme, pasta e líquido rejuvenescedor, protetor e para limpeza da pele, orgânico, inorgânico e sintético;Cremes cosméticos;Cremes para clarear a pele;Desodorante antiperspirante [desodorante antitranspirante];Desodorantes [perfumaria];Desumidificador em potes, à base de cloreto de cálcio, não elétrico;Enxaguantes bucais, exceto para uso medicinal;Erva para banho;Erva para defumador e incenso;Esmalte para unhas;Essência de badiana [anis estrelado];Essência de menta [óleo essencial];Essências etéreas;Estojo de cosméticos de brinquedo (com cosméticos reais);Estojos de cosméticos [kits de cosméticos];Extratos de ervas para fins cosméticos;Extratos de flores [perfumaria];Géis de massagem, exceto para uso medicinal;Géis para clareamento dental;Geleia de petróleo para uso cosmético;Gorduras para uso cosmético;Leite de amêndoas para uso cosmético;Leites de limpeza para toalete;Lenços impregnados com loções cosméticas;Lenços impregnados com preparações para remover maquiagem;Lenços umedecidos para bebês, impregnados com preparações para limpeza;Líquido, creme e pó para limpeza do dente;Loções capilares*;Loções para uso cosmético;Loções pós-barba;Máscaras de beleza;Mistura de fragrâncias;Odorizadores de uso pessoal;Óleo de amêndoas;Óleo de bergamota;Óleo de gaulteria [perfumaria];Óleo de jasmim;Óleo de lavanda;Óleo de rosa;Óleo de terebintina para desengordurar;Óleos essenciais;Óleos essenciais de cedro;Óleos essenciais de cidra;Óleos essenciais de limão;Óleos para limpeza;Óleos para perfumes e essências;Óleos para toalete;Óleos para uso cosmético;Panos impregnados com detergente para limpeza;Papel impregnado de substância para higiene pessoal;Parches em gel para os olhos para fins cosméticos;Perfumes;Pomadas para uso cosmético;Preparação cosmética para redução da gordura localizada;Preparações cosméticas para banhos;Preparações cosméticas para emagrecimento;Preparações de aloe vera para uso cosmético;Preparações de babosa para uso cosmético;Preparações de banho para higiene íntima ou para uso desodorante [produtos de higiene pessoal];Preparações de colágeno para fins cosméticos;Preparações de limpeza para fins de higiene íntima pessoal, não medicinais;Preparações depilatórias;Preparações fitocosméticas;Preparações para alisar cabelos;Preparações para banho de espuma, exceto para uso medicinal;Preparações para banho de imersão de uso pessoal, exceto para uso medicinal;Preparações para banho, exceto para fins medicinais;Preparações para barbear;Preparações para bronzear [cosméticos];Preparações para higiene pessoal*;Preparações para ondular os cabelos;Preparações para perfumar ambientes;Preparações para refrescar o hálito para higiene pessoal;Produto para limpeza e hidratação da pele não medicamentoso;Produtos cosméticos para cuidados da pele;Produtos cosméticos para os cílios;Produtos de perfumaria;Produtos para maquiagem;Produtos para o cuidado das unhas;Produtos para remover maquiagem;Removedor de cosmético;Removedores de esmalte de unhas;Sabões*;Sabonete antitranspirante;Sabonete antitranspirante para os pés;Sabonete de amêndoas;Sabonete desodorante;Sabonete para barbear;Sabonetes;Sachê com sílica gel para higienização [desumidificador];Sachês para perfumar roupa;Sais de banho, exceto para uso medicinal;Saponáceo;Talco para toalete;Tinturas cosméticas;Tinturas para barba;Tinturas para os cabelos;Varetas de incenso;Xampu a seco*;Xampus*;","status":"Pendente"}},"procurador":"RITTER E MORAES PROPRIEDADE INTELECTUAL S/S"}