{"numero":"919102077","data-deposito":"28/01/2020","despachos":{"despacho":{"codigo":"IPAS009","nome":"Publicação de pedido de registro para oposição (exame formal concluído)"}},"titulares":{"titular":{"nome-razao-social":"MJN U.S. HOLDINGS LLC","pais":"US","uf":""}},"marca":{"apresentacao":"Nominativa","natureza":"Produtos e/ou Serviço","nome":"ENFAMIL M-COMPLEX"},"lista-classe-nice":{"classe-nice":{"codigo":"30","especificacao":"Cereais para consumo humano, barras nutricionais a base de cereais; aperitivos em forma de barra inclusos nesta classe; bebidas à base de cacau ou chocolate inclusas nesta classe.;","status":"Pendente (com especificação livre)"}},"procurador":"EDUARDO LOURENÇO GUEDES SERRÃO DE OTERO"}