{"numero":"919134688","data-deposito":"31/01/2020","despachos":{"despacho":{"codigo":"IPAS009","nome":"Publicação de pedido de registro para oposição (exame formal concluído)"}},"titulares":{"titular":{"nome-razao-social":"LAURO FERNANDO GOMES 00874401135","pais":"BR","uf":"GO"}},"marca":{"apresentacao":"Mista","natureza":"Produtos e/ou Serviço","nome":"BORRACHARIA LR"},"classes-vienna":{"edicao":"4","classe-vienna":[{"codigo":"27.5.1"},{"codigo":"29.1.12"}]},"lista-classe-nice":{"classe-nice":{"codigo":"37","especificacao":"Instalação e reparo de aparelhos elétricos;Lubrificação de veículos;Manutenção de veículos;Manutenção e reparo de automóveis;serviços de borracharia;","status":"Pendente"}},"procurador":"MARIA BETANIA SONIA DE SOUZA"}