{"numero":"919122469","data-deposito":"30/01/2020","despachos":{"despacho":{"codigo":"IPAS009","nome":"Publicação de pedido de registro para oposição (exame formal concluído)"}},"titulares":{"titular":{"nome-razao-social":"GLOBO COMUNICAÇÃO E PARTICIPAÇÕES S.A.","pais":"BR","uf":"RJ"}},"marca":{"apresentacao":"Mista","natureza":"Produtos e/ou Serviço","nome":"JUNTAÊ"},"classes-vienna":{"edicao":"4","classe-vienna":[{"codigo":"27.5.3"},{"codigo":"27.5.9"},{"codigo":"27.5.17"}]},"lista-classe-nice":{"classe-nice":{"codigo":"03","especificacao":"Adesivos para enfeitar unhas;Cosméticos;Dentifrícios*;Desodorantes [perfumaria];Esmalte para unhas;Loções capilares*;Loções para uso cosmético;Maquiagem para o rosto;Óleos essenciais;Óleos para perfumes e essências;Óleos para toalete;Óleos para uso cosmético;Perfumes;Pomadas para uso cosmético;Preparações de banho para higiene íntima ou para uso desodorante [produtos de higiene pessoal];Preparações para perfumar ambientes;Preparações para proteção solar;Produtos cosméticos para cuidados da pele;Produtos de perfumaria;Produtos para maquiagem;Produtos para o cuidado das unhas;Sabões*;Sabonetes;Talco para toalete;Xampus*;","status":"Pendente"}},"procurador":"Matos & Associados - Advogados"}